mulch/__init__.py
mulch/about_this_workspace.md
mulch/active_workspace_manager.py
mulch/basepath_manager.py
mulch/cli.py
mulch/commands/build_dotmulch_standard_contents.py
mulch/commands/dotfolder.py
mulch/constants.py
mulch/decorators.py
mulch/default-config.toml
mulch/default-queries.toml
mulch/default-workspace.toml
mulch/deprecated/build-local-mulch-dir.ps1
mulch/deprecated/install-mulch-context-by-running-reg.ps1
mulch/deprecated/install-mulch-workspace-localappdata.reg
mulch/deprecated/install-mulch-workspace-userprofile.reg
mulch/flags_log_status.py
mulch/helpers.py
mulch/logging.json
mulch/logging_setup.py
mulch/paths.py
mulch/reference_lock_manager.py
mulch/reg_backup-localappdata.py
mulch/reg_winreg.py
mulch/sandbox.py
mulch/scaffold_loader.py
mulch/scripts/install/.mulchvision
mulch/scripts/install/call-mulch-seed.ps1
mulch/scripts/install/call-mulch-workspace.ps1
mulch/scripts/install/install_context.py
mulch/scripts/install/mulch-icon.ico
mulch/scripts/install/mulch-seed.desktop
mulch/scripts/install/mulch-seed.ps1
mulch/scripts/install/mulch-workspace.desktop
mulch/scripts/install/mulch-workspace.ps1
mulch/scripts/install/pipx install mulch.ps1
mulch/state_manager.py
mulch/templates/__init__.py
mulch/templates/about_this_workspace.md.j2
mulch/templates/workspace_manager.py.j2
mulch/workspace_instance_factory.py
mulch/workspace_manager_generator.py
mulch/workspace_status.py
mulch-0.2.65.dist-info/entry_points.txt
mulch-0.2.65.dist-info/LICENSE
mulch-0.2.65.dist-info/METADATA
mulch-0.2.65.dist-info/WHEEL
mulch-0.2.65.dist-info/RECORD
