Metadata-Version: 2.3
Name: mulch
Version: 0.2.65
Summary: Pythonic Typer CLI for bootstrapping standard and templated workspaces and projects. Generate introspective sourcecode workspace_manager.py Path quarterback. Controlled per-directory scaffolds using the mulch.toml file. Stealth options available for directories shared between dev and non-dev team members.
Author: George Clayton Bennett
Author-email: george.bennett@memphistn.gov
Requires-Python: >=3.11,<4.0
Classifier: Programming Language :: Python :: 3
Classifier: Programming Language :: Python :: 3.11
Classifier: Programming Language :: Python :: 3.12
Classifier: Programming Language :: Python :: 3.13
Requires-Dist: click (<8.1.7)
Requires-Dist: jinja2 (>=3.1.6,<4.0.0)
Requires-Dist: rich (<13.7.0)
Requires-Dist: toml (>=0.10.2,<0.11.0)
Requires-Dist: typer (>=0.12.3,<0.13.0)
